onnx2kerastl/__init__.py
onnx2kerastl/activation_layers.py
onnx2kerastl/caffe2_layers.py
onnx2kerastl/constant_layers.py
onnx2kerastl/convert_model.py
onnx2kerastl/converter.py
onnx2kerastl/convolution_layers.py
onnx2kerastl/customonnxlayer/__init__.py
onnx2kerastl/customonnxlayer/onnxabs.py
onnx2kerastl/customonnxlayer/onnxeinsum.py
onnx2kerastl/customonnxlayer/onnxerf.py
onnx2kerastl/customonnxlayer/onnxhardsigmoid.py
onnx2kerastl/customonnxlayer/onnxlstm.py
onnx2kerastl/customonnxlayer/onnxreducemean.py
onnx2kerastl/customonnxlayer/onnxsqrt.py
onnx2kerastl/elementwise_layers.py
onnx2kerastl/exceptions.py
onnx2kerastl/fft_layers.py
onnx2kerastl/layers.py
onnx2kerastl/linear_layers.py
onnx2kerastl/ltsm_layers.py
onnx2kerastl/main.py
onnx2kerastl/normalization_layers.py
onnx2kerastl/operation_layers.py
onnx2kerastl/padding_layers.py
onnx2kerastl/pooling_layers.py
onnx2kerastl/reshape_layers.py
onnx2kerastl/sampling_layers.py
onnx2kerastl/tfops_funcs.py
onnx2kerastl/upsampling_layers.py
onnx2kerastl/utils.py
onnx2kerastl-0.0.186.dist-info/LICENSE
onnx2kerastl-0.0.186.dist-info/METADATA
onnx2kerastl-0.0.186.dist-info/WHEEL
onnx2kerastl-0.0.186.dist-info/RECORD
