Metadata-Version: 2.3
Name: onnx2kerastl
Version: 0.0.186
Summary: 
License: MIT
Author: dorhar
Author-email: doron.harnoy@tensorleap.ai
Requires-Python: >=3.8,<3.11
Classifier: License :: OSI Approved :: MIT License
Classifier: Programming Language :: Python :: 3
Classifier: Programming Language :: Python :: 3.8
Classifier: Programming Language :: Python :: 3.9
Classifier: Programming Language :: Python :: 3.10
Requires-Dist: boto3 (>=1.24.22,<2.0.0)
Requires-Dist: fvcore (>=0.1.5.post20221221,<0.2.0)
Requires-Dist: keras-data-format-converter (==0.1.24)
Requires-Dist: numpy (==1.23.5)
Requires-Dist: onnx (==1.13.0)
Requires-Dist: protobuf (>=3.19.6,<4.0.0)
Requires-Dist: tensorflow (==2.12.0) ; platform_machine == "x86_64"
Requires-Dist: tensorflow-addons (>=0.19.0,<0.20.0) ; platform_machine == "x86_64"
Requires-Dist: tensorflow-io-gcs-filesystem (==0.34.0)
Requires-Dist: tensorflow-macos (==2.12.0) ; platform_machine == "arm64"
